tpl/__init__.py
tpl/auth.py
tpl/cache.py
tpl/cli.py
tpl/errors.py
tpl/lockfile.py
tpl/project.py
tpl/specs.py
tpl/template.py
tpl_cli-0.2.0.dist-info/METADATA
tpl_cli-0.2.0.dist-info/WHEEL
tpl_cli-0.2.0.dist-info/entry_points.txt
tpl_cli-0.2.0.dist-info/top_level.txt
tpl_cli-0.2.0.dist-info/RECORD
