Metadata-Version: 2.4
Name: tpl-cli
Version: 0.2.0
Summary: A CLI that composes single-file Cookiecutter templates via Git
Author: tpl Maintainers
License: MIT
Project-URL: Homepage, https://github.com/your-org/tpl
Project-URL: Repository, https://github.com/your-org/tpl
Project-URL: Documentation, https://github.com/your-org/tpl#readme
Project-URL: Issues, https://github.com/your-org/tpl/issues
Keywords: cookiecutter,templates,cli
Classifier: Development Status :: 3 - Alpha
Classifier: Intended Audience :: Developers
Classifier: License :: OSI Approved :: MIT License
Classifier: Programming Language :: Python
Classifier: Programming Language :: Python :: 3
Classifier: Programming Language :: Python :: 3.8
Classifier: Programming Language :: Python :: 3.9
Classifier: Programming Language :: Python :: 3.10
Classifier: Programming Language :: Python :: 3.11
Classifier: Programming Language :: Python :: 3.12
Classifier: Programming Language :: Python :: 3.13
Classifier: Programming Language :: Python :: 3.14
Requires-Python: <3.15,>=3.8
Requires-Dist: cookiecutter
Requires-Dist: tomli; python_version < "3.11"
Provides-Extra: dev
Requires-Dist: pytest; extra == "dev"
Requires-Dist: mypy; extra == "dev"
Requires-Dist: ruff; extra == "dev"
Requires-Dist: pre-commit; extra == "dev"
Requires-Dist: tox; extra == "dev"
